LICENSE
MANIFEST.in
README.rst
setup.py
docs/Makefile
docs/conf.py
docs/index.rst
docs/_build/doctrees/environment.pickle
docs/_build/doctrees/index.doctree
docs/_build/doctrees/modules/query.doctree
docs/_build/doctrees/modules/rest_function.doctree
docs/_build/doctrees/modules/routers.doctree
docs/_build/doctrees/modules/serializers.doctree
docs/_build/doctrees/modules/serve.doctree
docs/_build/doctrees/modules/views.doctree
docs/_build/html/.buildinfo
docs/_build/html/genindex.html
docs/_build/html/index.html
docs/_build/html/objects.inv
docs/_build/html/py-modindex.html
docs/_build/html/search.html
docs/_build/html/searchindex.js
docs/_build/html/_sources/index.txt
docs/_build/html/_sources/modules/query.txt
docs/_build/html/_sources/modules/rest_function.txt
docs/_build/html/_sources/modules/routers.txt
docs/_build/html/_sources/modules/serializers.txt
docs/_build/html/_sources/modules/serve.txt
docs/_build/html/_sources/modules/views.txt
docs/_build/html/_static/ajax-loader.gif
docs/_build/html/_static/alabaster.css
docs/_build/html/_static/basic.css
docs/_build/html/_static/classic.css
docs/_build/html/_static/comment-bright.png
docs/_build/html/_static/comment-close.png
docs/_build/html/_static/comment.png
docs/_build/html/_static/doctools.js
docs/_build/html/_static/down-pressed.png
docs/_build/html/_static/down.png
docs/_build/html/_static/file.png
docs/_build/html/_static/jquery-1.11.1.js
docs/_build/html/_static/jquery.js
docs/_build/html/_static/minus.png
docs/_build/html/_static/plus.png
docs/_build/html/_static/pygments.css
docs/_build/html/_static/searchtools.js
docs/_build/html/_static/sidebar.js
docs/_build/html/_static/underscore-1.3.1.js
docs/_build/html/_static/underscore.js
docs/_build/html/_static/up-pressed.png
docs/_build/html/_static/up.png
docs/_build/html/_static/websupport.js
docs/_build/html/modules/query.html
docs/_build/html/modules/rest_function.html
docs/_build/html/modules/routers.html
docs/_build/html/modules/serializers.html
pumpwood_viewutils.egg-info/PKG-INFO
pumpwood_viewutils.egg-info/SOURCES.txt
pumpwood_viewutils.egg-info/dependency_links.txt
pumpwood_viewutils.egg-info/pbr.json
pumpwood_viewutils.egg-info/requires.txt
pumpwood_viewutils.egg-info/top_level.txt