Metadata-Version: 1.0
Name: pumpwood-viewutils
Version: 0.3.9.1
Summary: Define views, serializers and routers as the PumpWood format
Home-page: UNKNOWN
Author: André Andrade Baceti
Author-email: a.baceti@murabei.com
License: UNKNOWN
Platform: UNKNOWN
